ziggo_mediabox_xl.py
ziggo_mediabox_xl-1.1.0.dist-info/DESCRIPTION.rst
ziggo_mediabox_xl-1.1.0.dist-info/METADATA
ziggo_mediabox_xl-1.1.0.dist-info/RECORD
ziggo_mediabox_xl-1.1.0.dist-info/WHEEL
ziggo_mediabox_xl-1.1.0.dist-info/metadata.json
ziggo_mediabox_xl-1.1.0.dist-info/top_level.txt
