Metadata-Version: 1.1
Name: ziggo-mediabox-xl
Version: 1.1.0
Summary: Python interface to Ziggo's Mediabox XL
Home-page: https://github.com/b10m/ziggo_mediabox_xl
Author: Menno Blom
Author-email: menno@b10m.net
License: MIT license
Keywords: ziggo_mediabox_xl
Platform: UNKNOWN
Classifier: Development Status :: 2 - Pre-Alpha
Classifier: Intended Audience :: Developers
Classifier: License :: OSI Approved :: MIT License
Classifier: Natural Language :: English
Classifier: Programming Language :: Python :: 3
Classifier: Programming Language :: Python :: 3.3
Classifier: Programming Language :: Python :: 3.4
Classifier: Programming Language :: Python :: 3.5
